Rofi_MPD-2.2.1.data/scripts/rofi-mpd
rofi/__init__.py
rofi/rofi.py
rofi_mpd/__init__.py
rofi_mpd/config.py
rofi_mpd/date_parser.py
rofi_mpd/rofi_mpd.py
Rofi_MPD-2.2.1.dist-info/LICENSE
Rofi_MPD-2.2.1.dist-info/METADATA
Rofi_MPD-2.2.1.dist-info/WHEEL
Rofi_MPD-2.2.1.dist-info/top_level.txt
Rofi_MPD-2.2.1.dist-info/RECORD
