Metadata-Version: 2.1
Name: Rofi-MPD
Version: 2.2.1
Summary: A Rofi menu for interacting with MPD.
Home-page: https://github.com/JakeStanger/Rofi_MPD
Author: Jake Stanger
Author-email: mail@jstanger.dev
License: MIT
Platform: UNKNOWN
Requires-Dist: python-mpd2
Requires-Dist: mutagen
Requires-Dist: toml
Requires-Dist: appdirs
